pygiconverter_test_din/__init__.py
pygiconverter_test_din/converter.py
pygifconvert_test_din-1.0.0.dist-info/LICENSE
pygifconvert_test_din-1.0.0.dist-info/METADATA
pygifconvert_test_din-1.0.0.dist-info/WHEEL
pygifconvert_test_din-1.0.0.dist-info/top_level.txt
pygifconvert_test_din-1.0.0.dist-info/RECORD
